mathematics/__init__.py
mathematics/mathematics.py
math_extension-1.0.dist-info/METADATA
math_extension-1.0.dist-info/WHEEL
math_extension-1.0.dist-info/top_level.txt
math_extension-1.0.dist-info/RECORD
